LICENSE
README.md
setup.py
diakaplug/__init__.py
diakaplug.egg-info/PKG-INFO
diakaplug.egg-info/SOURCES.txt
diakaplug.egg-info/dependency_links.txt
diakaplug.egg-info/requires.txt
diakaplug.egg-info/top_level.txt