Metadata-Version: 2.1
Name: diakaplug
Version: 0.0.2
Summary: a simple python library to receive notifications from diaka.ua
Home-page: https://github.com/d3kxrma/diakaplug
Author: dekxrma
Author-email: qqdjnuxez@gmail.com
License: MIT
Keywords: python,diaka,diaka api,diakapy
Classifier: Development Status :: 5 - Production/Stable
Classifier: Intended Audience :: Developers
Classifier: Operating System :: Microsoft :: Windows :: Windows 10
Classifier: License :: OSI Approved :: MIT License
Classifier: Programming Language :: Python :: 3
License-File: LICENSE
